zcommons/__init__.py
zcommons/colorama.py
zcommons/config_dict.py
zcommons/counter.py
zcommons/dataclass.py
zcommons/module.py
zcommons/threadgroup.py
zcommons/time.py
zcommons/timer.py
zcommons/units.py
zcommons/tools/__init__.py
zcommons/tools/conf2json.py
zcommons/tools/time.py
zcommons-0.2.1.dist-info/LICENSE
zcommons-0.2.1.dist-info/METADATA
zcommons-0.2.1.dist-info/WHEEL
zcommons-0.2.1.dist-info/top_level.txt
zcommons-0.2.1.dist-info/RECORD
