Metadata-Version: 2.1
Name: zcommons
Version: 0.2.1
Summary: A collection of common utils for python.
Home-page: https://github.com/malanore-z/zcommons4p
Author: malanore.z
Author-email: malanore.z@gmail.com
Project-URL: Bug Tracker, https://github.com/malanore-z/zcommons4p/issues
Classifier: Intended Audience :: Developers
Classifier: Programming Language :: Python :: 3
Classifier: License :: OSI Approved :: MIT License
Classifier: Operating System :: OS Independent
Requires-Python: >=3.6
License-File: LICENSE
Requires-Dist: colorama
Requires-Dist: dataclasses ; python_version < "3.7"
